{
  "test_brokerage": [
    {
      "job_id": "email_1755726273_test_csv",
      "filename": "test.csv",
      "brokerage_key": "test_brokerage",
      "email_source": "test@example.com",
      "status": "processing",
      "progress_percent": 50.0,
      "current_step": "parsing_email",
      "started_at": "2025-08-20T16:44:33.392179",
      "completed_at": null,
      "record_count": 10,
      "success_count": 0,
      "failure_count": 0,
      "processing_time": 0.0,
      "error_message": "",
      "result_data": null
    }
  ],
  "test_pipeline": [
    {
      "job_id": "email_1755726334_pipeline_test_csv",
      "filename": "pipeline_test.csv",
      "brokerage_key": "test_pipeline",
      "email_source": "pipeline@test.com",
      "status": "completed",
      "progress_percent": 100.0,
      "current_step": "completed",
      "started_at": "2025-08-20T16:45:34.713157",
      "completed_at": "2025-08-20T16:45:34.713791",
      "record_count": 25,
      "success_count": 23,
      "failure_count": 2,
      "processing_time": 0.000635,
      "error_message": "",
      "result_data": null
    }
  ],
  "eShipping": [
    {
      "job_id": "email_1755726887_Testing- eShipping (1)_xlsx",
      "filename": "Testing- eShipping (1).xlsx",
      "brokerage_key": "eShipping",
      "email_source": "eshippingflatfiles@goaugment.com",
      "status": "completed",
      "progress_percent": 100.0,
      "current_step": "completed",
      "started_at": "2025-08-20T16:54:47.359076",
      "completed_at": "2025-08-20T16:54:47.359496",
      "record_count": 45,
      "success_count": 42,
      "failure_count": 3,
      "processing_time": 0.000422,
      "error_message": "",
      "result_data": null
    },
    {
      "job_id": "email_1755726887_Current Processing_csv",
      "filename": "Current Processing.csv",
      "brokerage_key": "eShipping",
      "email_source": "eshippingflatfiles@goaugment.com",
      "status": "processing",
      "progress_percent": 65.0,
      "current_step": "submitting_api",
      "started_at": "2025-08-20T16:54:47.359868",
      "completed_at": null,
      "record_count": 30,
      "success_count": 0,
      "failure_count": 0,
      "processing_time": 0.0,
      "error_message": "",
      "result_data": null
    },
    {
      "job_id": "email_1755786066_background_auto_1755786066_0_csv",
      "filename": "background_auto_1755786066_0.csv",
      "brokerage_key": "eShipping",
      "email_source": "eshippingflatfiles@goaugment.com",
      "status": "completed",
      "progress_percent": 100.0,
      "current_step": "completed",
      "started_at": "2025-08-21T09:21:06.306949",
      "completed_at": "2025-08-21T09:21:07.314919",
      "record_count": 40,
      "success_count": 39,
      "failure_count": 0,
      "processing_time": 1.007985,
      "error_message": "",
      "result_data": null
    },
    {
      "job_id": "email_1755786068_background_auto_1755786068_1_csv",
      "filename": "background_auto_1755786068_1.csv",
      "brokerage_key": "eShipping",
      "email_source": "eshippingflatfiles@goaugment.com",
      "status": "completed",
      "progress_percent": 100.0,
      "current_step": "completed",
      "started_at": "2025-08-21T09:21:08.320147",
      "completed_at": "2025-08-21T09:21:09.333243",
      "record_count": 48,
      "success_count": 20,
      "failure_count": 2,
      "processing_time": 1.013107,
      "error_message": "",
      "result_data": null
    },
    {
      "job_id": "email_1755786070_background_auto_1755786070_2_csv",
      "filename": "background_auto_1755786070_2.csv",
      "brokerage_key": "eShipping",
      "email_source": "eshippingflatfiles@goaugment.com",
      "status": "completed",
      "progress_percent": 100.0,
      "current_step": "completed",
      "started_at": "2025-08-21T09:21:10.338804",
      "completed_at": "2025-08-21T09:21:11.348327",
      "record_count": 27,
      "success_count": 22,
      "failure_count": 0,
      "processing_time": 1.009537,
      "error_message": "",
      "result_data": null
    }
  ]
}